{
  "user_id": "2387782862800",
  "name": "Artur",
  "liked_jobs": [],
  "disliked_jobs": [],
  "applied_jobs": [],
  "saved_jobs": [],
  "rejected_job_types": [],
  "preferred_companies": [],
  "avoided_companies": [],
  "confirmed_skills": [],
  "desired_skills": [],
  "career_interests": [],
  "prefers_remote": null,
  "prefers_startup": null,
  "prefers_large_company": null,
  "salary_expectations": null,
  "search_queries": [],
  "feedback_history": [],
  "created_at": "2025-12-09T23:03:39.448609",
  "last_active": "2025-12-09T23:04:00.300679"
}